[
  { "id": "AL", "val": "01", "objectID": "B9IfALchYP" },
  { "id": "AK", "val": "02", "objectID": "UGNHGooffs" },
  { "id": "AS", "val": "60", "objectID": "zq8GVoD1n0" },
  { "id": "AZ", "val": "04", "objectID": "9DhrhBxbKN" },
  { "id": "AR", "val": "05", "objectID": "B9IfALchYP" },
  { "id": "CA", "val": "06", "objectID": "B9IfALchYP" },
  { "id": "CO", "val": "08", "objectID": "B9IfALchYP" },
  { "id": "CT", "val": "09", "objectID": "B9IfALchYP" },
  { "id": "DE", "val": "10", "objectID": "B9IfALchYP" },
  { "id": "DC", "val": "11", "objectID": "B9IfALchYP" },
  { "id": "FL", "val": "12", "objectID": "B9IfALchYP" },
  { "id": "FM", "val": "64", "objectID": "B9IfALchYP" },
  { "id": "GA", "val": "13", "objectID": "B9IfALchYP" },
  { "id": "GU", "val": "66", "objectID": "B9IfALchYP" },
  { "id": "HI", "val": "15", "objectID": "B9IfALchYP" },
  { "id": "ID", "val": "16", "objectID": "B9IfALchYP" },
  { "id": "IL", "val": "17", "objectID": "B9IfALchYP" },
  { "id": "IN", "val": "18", "objectID": "B9IfALchYP" },
  { "id": "IA", "val": "19", "objectID": "B9IfALchYP" },
  { "id": "KS", "val": "20", "objectID": "B9IfALchYP" },
  { "id": "KY", "val": "21", "objectID": "B9IfALchYP" },
  { "id": "LA", "val": "22", "objectID": "B9IfALchYP" },
  { "id": "ME", "val": "23", "objectID": "B9IfALchYP" },
  { "id": "MH", "val": "68", "objectID": "B9IfALchYP" },
  { "id": "MD", "val": "24", "objectID": "B9IfALchYP" },
  { "id": "MA", "val": "25", "objectID": "B9IfALchYP" },
  { "id": "MI", "val": "26", "objectID": "B9IfALchYP" },
  { "id": "MN", "val": "27", "objectID": "B9IfALchYP" },
  { "id": "MS", "val": "28", "objectID": "B9IfALchYP" },
  { "id": "MO", "val": "29", "objectID": "B9IfALchYP" },
  { "id": "MT", "val": "30", "objectID": "B9IfALchYP" },
  { "id": "NE", "val": "31", "objectID": "B9IfALchYP" },
  { "id": "NV", "val": "32", "objectID": "B9IfALchYP" },
  { "id": "NH", "val": "33", "objectID": "B9IfALchYP" },
  { "id": "NJ", "val": "34", "objectID": "B9IfALchYP" },
  { "id": "NM", "val": "35", "objectID": "B9IfALchYP" },
  { "id": "NY", "val": "36", "objectID": "B9IfALchYP" },
  { "id": "NC", "val": "37", "objectID": "B9IfALchYP" },
  { "id": "ND", "val": "38", "objectID": "B9IfALchYP" },
  { "id": "MP", "val": "69", "objectID": "B9IfALchYP" },
  { "id": "OH", "val": "39", "objectID": "B9IfALchYP" },
  { "id": "OK", "val": "40", "objectID": "B9IfALchYP" },
  { "id": "OR", "val": "41", "objectID": "B9IfALchYP" },
  { "id": "PW", "val": "70", "objectID": "B9IfALchYP" },
  { "id": "PA", "val": "42", "objectID": "B9IfALchYP" },
  { "id": "PR", "val": "72", "objectID": "B9IfALchYP" },
  { "id": "RI", "val": "44", "objectID": "B9IfALchYP" },
  { "id": "SC", "val": "45", "objectID": "B9IfALchYP" },
  { "id": "SD", "val": "46", "objectID": "B9IfALchYP" },
  { "id": "TN", "val": "47", "objectID": "B9IfALchYP" },
  { "id": "TX", "val": "48", "objectID": "B9IfALchYP" },
  { "id": "UM", "val": "74", "objectID": "B9IfALchYP" },
  { "id": "UT", "val": "49", "objectID": "B9IfALchYP" },
  { "id": "VT", "val": "50", "objectID": "B9IfALchYP" },
  { "id": "VA", "val": "51", "objectID": "B9IfALchYP" },
  { "id": "VI", "val": "78", "objectID": "B9IfALchYP" },
  { "id": "WA", "val": "53", "objectID": "B9IfALchYP" },
  { "id": "WV", "val": "54", "objectID": "B9IfALchYP" },
  { "id": "WI", "val": "55", "objectID": "B9IfALchYP" },
  { "id": "WY", "val": "56", "objectID": "B9IfALchYP" }
]
